sherpa_ml/__about__.py
sherpa_ml/__init__.py
sherpa_ml/cli.py
sherpa_ml/context.py
sherpa_ml/plugins.py
sherpa_ml/render.py
sherpa_ml/telemetry.py
sherpa_ml/utils.py
sherpa_ml/templates/common/CODE_OF_CONDUCT.md.j2
sherpa_ml/templates/common/CONTRIBUTING.md.j2
sherpa_ml/templates/common/DATA_CARD.md.j2
sherpa_ml/templates/common/LICENSE.j2
sherpa_ml/templates/common/MODEL_CARD.md.j2
sherpa_ml/templates/common/Makefile.j2
sherpa_ml/templates/common/README.md.j2
sherpa_ml/templates/common/SECURITY.md.j2
sherpa_ml/templates/common/docker-compose.yml.j2
sherpa_ml/templates/common/dvc.yaml.j2
sherpa_ml/templates/common/pyproject.toml.j2
sherpa_ml/templates/common/conf/config.yaml.j2
sherpa_ml/templates/common/conf/eval/default.yaml.j2
sherpa_ml/templates/common/conf/train/default.yaml.j2
sherpa_ml/templates/common/docker/cuda.Dockerfile.j2
sherpa_ml/templates/common/docker/slim.Dockerfile.j2
sherpa_ml/templates/common/scripts/download_data.py.j2
sherpa_ml/templates/common/scripts/prepare_data.py.j2
sherpa_ml/templates/common/src/{{ pkg }}/serve/app.py.j2
sherpa_ml/templates/common/src/{{ pkg }}/utils/config.py.j2
sherpa_ml/templates/common/src/{{ pkg }}/utils/logging.py.j2
sherpa_ml/templates/common/src/{{ pkg }}/utils/paths.py.j2
sherpa_ml/templates/common/src/{{ pkg }}/utils/tracking.py.j2
sherpa_ml/templates/presets/minimal/conf/config.yaml.j2
sherpa_ml/templates/presets/minimal/src/{{ pkg }}/__init__.py.j2
sherpa_ml/templates/presets/minimal/src/{{ pkg }}/eval.py.j2
sherpa_ml/templates/presets/minimal/src/{{ pkg }}/infer.py.j2
sherpa_ml/templates/presets/minimal/src/{{ pkg }}/train.py.j2
sherpa_ml/templates/presets/minimal/src/{{ pkg }}/utils/logging.py.j2
sherpa_ml/templates/presets/minimal/src/{{ pkg }}/utils/paths.py.j2
sherpa_ml/templates/presets/minimal/tests/test_smoke.py.j2
sherpa_ml/templates/presets/nlp/conf/config.yaml.j2
sherpa_ml/templates/presets/nlp/conf/eval/default.yaml.j2
sherpa_ml/templates/presets/nlp/conf/train/default.yaml.j2
sherpa_ml-0.1.3.dist-info/licenses/LICENSE
sherpa_ml-0.1.3.dist-info/METADATA
sherpa_ml-0.1.3.dist-info/WHEEL
sherpa_ml-0.1.3.dist-info/entry_points.txt
sherpa_ml-0.1.3.dist-info/top_level.txt
sherpa_ml-0.1.3.dist-info/RECORD
