Metadata-Version: 2.4
Name: sherpa-ml
Version: 0.1.3
Summary: Sherpa-ML: production-grade ML repo scaffolder with presets (vision/tabular/nlp/minimal), Hydra, MLflow, Docker, CI.
Author: Abdulvahap Mutlu
License: MIT
Project-URL: Homepage, https://github.com/abdulvahapmutlu/sherpa-ml
Project-URL: Issues, https://github.com/abdulvahapmutlu/sherpa-ml/issues
Classifier: Programming Language :: Python :: 3
Classifier: Programming Language :: Python :: 3.10
Classifier: Programming Language :: Python :: 3.11
Classifier: Programming Language :: Python :: 3.12
Classifier: License :: OSI Approved :: MIT License
Classifier: Intended Audience :: Science/Research
Classifier: Topic :: Scientific/Engineering :: Artificial Intelligence
Classifier: Typing :: Typed
Requires-Python: >=3.10
License-File: LICENSE
Requires-Dist: typer>=0.12.3
Requires-Dist: jinja2>=3.1.4
Requires-Dist: pydantic>=2.8.0
Requires-Dist: rich>=13.7.1
Requires-Dist: platformdirs>=4.2.2
Provides-Extra: dev
Requires-Dist: pytest>=8.2.0; extra == "dev"
Requires-Dist: mypy>=1.11.0; extra == "dev"
Requires-Dist: ruff>=0.6.5; extra == "dev"
Requires-Dist: black>=24.8.0; extra == "dev"
Requires-Dist: types-setuptools; extra == "dev"
Dynamic: license-file
